[{"collection": "Breakout", "weapon": "MP7", "name": "Urban Hazard", "grade": "Mil-Spec", "link": "https://steamcommunity.com/market/search?appid=730&q=MP7+Urban+Hazard"},{"collection": "Breakout", "weapon": "Negev", "name": "Desert-Strike", "grade": "Mil-Spec", "link": "https://steamcommunity.com/market/search?appid=730&q=Negev+Desert-Strike"},{"collection": "Breakout", "weapon": "P2000", "name": "Ivory", "grade": "Mil-Spec", "link": "https://steamcommunity.com/market/search?appid=730&q=P2000+Ivory"},{"collection": "Breakout", "weapon": "SSG 08", "name": "Abyss", "grade": "Mil-Spec", "link": "https://steamcommunity.com/market/search?appid=730&q=SSG 08+Abyss"},{"collection": "Breakout", "weapon": "UMP-45", "name": "Labyrinth", "grade": "Mil-Spec", "link": "https://steamcommunity.com/market/search?appid=730&q=UMP-45+Labyrinth"},{"collection": "Breakout", "weapon": "PP-Bizon", "name": "Osiris", "grade": "Restricted", "link": "https://steamcommunity.com/market/search?appid=730&q=PP-Bizon+Osiris"},{"collection": "Breakout", "weapon": "CZ75-Auto", "name": "Tigris", "grade": "Restricted", "link": "https://steamcommunity.com/market/search?appid=730&q=CZ75-Auto+Tigris"},{"collection": "Breakout", "weapon": "Nova", "name": "Koi", "grade": "Restricted", "link": "https://steamcommunity.com/market/search?appid=730&q=Nova+Koi"},{"collection": "Breakout", "weapon": "P250", "name": "Supernova", "grade": "Restricted", "link": "https://steamcommunity.com/market/search?appid=730&q=P250+Supernova"},{"collection": "Breakout", "weapon": "Desert Eagle", "name": "Conspiracy", "grade": "Classified", "link": "https://steamcommunity.com/market/search?appid=730&q=Desert Eagle+Conspiracy"},{"collection": "Breakout", "weapon": "Five-SeveN", "name": "Fowl Play", "grade": "Classified", "link": "https://steamcommunity.com/market/search?appid=730&q=Five-SeveN+Fowl+Play"},{"collection": "Breakout", "weapon": "Glock-18", "name": "Water Elemental", "grade": "Classified", "link": "https://steamcommunity.com/market/search?appid=730&q=Glock-18+Water+Elemental"},{"collection": "Breakout", "weapon": "P90", "name": "Asiimov", "grade": "Covert", "link": "https://steamcommunity.com/market/search?appid=730&q=P90+Asiimov"},{"collection": "Breakout", "weapon": "M4A1-S", "name": "Cyrex", "grade": "Covert", "link": "https://steamcommunity.com/market/search?appid=730&q=M4A1-S+Cyrex"}]